[
  {
    "date": "2026-07-11",
    "game_pk": 823357,
    "away_team": "Milwaukee Brewers",
    "home_team": "Pittsburgh Pirates",
    "venue": "PNC Park",
    "park_factor": 0.97,
    "temp_f": 72.0,
    "wind_mph": 5.0,
    "dome": false,
    "away_pitcher": "Brandon Sproat",
    "away_pitcher_1st_era": 5.4,
    "away_pitcher_season_era": 5.13,
    "away_pitcher_k_pct": 25.0,
    "home_pitcher": "Braxton Ashcraft",
    "home_pitcher_1st_era": 3.0,
    "home_pitcher_season_era": 3.24,
    "home_pitcher_k_pct": 27.8,
    "p_nrfi": 0.3058,
    "p_yrfi": 0.6942,
    "fair_nrfi": 227,
    "fair_yrfi": -227,
    "verdict": "BET YRFI",
    "side": "YRFI",
    "price": -108,
    "book": "FanDuel",
    "edge": 0.1749,
    "kelly_pct": 0.091,
    "stake": 90.97,
    "result": null,
    "runs_in_first": null,
    "pnl": null
  },
  {
    "date": "2026-07-11",
    "game_pk": 823356,
    "away_team": "Milwaukee Brewers",
    "home_team": "Pittsburgh Pirates",
    "venue": "PNC Park",
    "park_factor": 0.97,
    "temp_f": 72.0,
    "wind_mph": 5.0,
    "dome": false,
    "away_pitcher": "Shane Drohan",
    "away_pitcher_1st_era": 2.25,
    "away_pitcher_season_era": 2.97,
    "away_pitcher_k_pct": 22.8,
    "home_pitcher": "Bubba Chandler",
    "home_pitcher_1st_era": 4.76,
    "home_pitcher_season_era": 4.82,
    "home_pitcher_k_pct": 19.8,
    "p_nrfi": 0.3594,
    "p_yrfi": 0.6406,
    "fair_nrfi": 178,
    "fair_yrfi": -178,
    "verdict": "BET YRFI",
    "side": "YRFI",
    "price": -108,
    "book": "FanDuel",
    "edge": 0.1214,
    "kelly_pct": 0.0631,
    "stake": 63.13,
    "result": null,
    "runs_in_first": null,
    "pnl": null
  },
  {
    "date": "2026-07-11",
    "game_pk": 823682,
    "away_team": "Los Angeles Angels",
    "home_team": "Minnesota Twins",
    "venue": "Target Field",
    "park_factor": 0.97,
    "temp_f": 88.0,
    "wind_mph": 7.0,
    "dome": false,
    "away_pitcher": "Ryan Johnson",
    "away_pitcher_1st_era": 14.4,
    "away_pitcher_season_era": 6.99,
    "away_pitcher_k_pct": 18.3,
    "home_pitcher": "Joe Ryan",
    "home_pitcher_1st_era": 3.93,
    "home_pitcher_season_era": 2.85,
    "home_pitcher_k_pct": 28.8,
    "p_nrfi": 0.1674,
    "p_yrfi": 0.8326,
    "fair_nrfi": 497,
    "fair_yrfi": -497,
    "verdict": "BET YRFI",
    "side": "YRFI",
    "price": 100,
    "book": "FanDuel",
    "edge": 0.3326,
    "kelly_pct": 0.1663,
    "stake": 166.3,
    "result": null,
    "runs_in_first": null,
    "pnl": null
  },
  {
    "date": "2026-07-11",
    "game_pk": 824576,
    "away_team": "Athletics",
    "home_team": "Chicago White Sox",
    "venue": "Rate Field",
    "park_factor": 0.92,
    "temp_f": 72.0,
    "wind_mph": 5.0,
    "dome": false,
    "away_pitcher": "Gage Jump",
    "away_pitcher_1st_era": 2.25,
    "away_pitcher_season_era": 3.77,
    "away_pitcher_k_pct": 22.7,
    "home_pitcher": "Bryan Hudson",
    "home_pitcher_1st_era": 1.8,
    "home_pitcher_season_era": 2.25,
    "home_pitcher_k_pct": 22.8,
    "p_nrfi": 0.5884,
    "p_yrfi": 0.4116,
    "fair_nrfi": -143,
    "fair_yrfi": 143,
    "verdict": "BET NRFI",
    "side": "NRFI",
    "price": -107,
    "book": "BetRivers",
    "edge": 0.0715,
    "kelly_pct": 0.037,
    "stake": 36.98,
    "result": null,
    "runs_in_first": null,
    "pnl": null
  },
  {
    "date": "2026-07-11",
    "game_pk": 823198,
    "away_team": "Colorado Rockies",
    "home_team": "San Francisco Giants",
    "venue": "Oracle Park",
    "park_factor": 0.9,
    "temp_f": 72.0,
    "wind_mph": 5.0,
    "dome": false,
    "away_pitcher": "Kyle Freeland",
    "away_pitcher_1st_era": 7.88,
    "away_pitcher_season_era": 7.46,
    "away_pitcher_k_pct": 18.5,
    "home_pitcher": "Tyler Mahle",
    "home_pitcher_1st_era": 6.43,
    "home_pitcher_season_era": 5.7,
    "home_pitcher_k_pct": 22.4,
    "p_nrfi": 0.1531,
    "p_yrfi": 0.8469,
    "fair_nrfi": 553,
    "fair_yrfi": -553,
    "verdict": "BET YRFI",
    "side": "YRFI",
    "price": -110,
    "book": "BetMGM",
    "edge": 0.3231,
    "kelly_pct": 0.1696,
    "stake": 169.61,
    "result": null,
    "runs_in_first": null,
    "pnl": null
  },
  {
    "date": "2026-07-11",
    "game_pk": 822711,
    "away_team": "New York Yankees",
    "home_team": "Washington Nationals",
    "venue": "Nationals Park",
    "park_factor": 0.96,
    "temp_f": 86.9,
    "wind_mph": 3.7,
    "dome": false,
    "away_pitcher": "Cam Schlittler",
    "away_pitcher_1st_era": 2.37,
    "away_pitcher_season_era": 2.01,
    "away_pitcher_k_pct": 29.6,
    "home_pitcher": "Miles Mikolas",
    "home_pitcher_1st_era": 5.4,
    "home_pitcher_season_era": 5.78,
    "home_pitcher_k_pct": 13.0,
    "p_nrfi": 0.3247,
    "p_yrfi": 0.6753,
    "fair_nrfi": 208,
    "fair_yrfi": -208,
    "verdict": "BET YRFI",
    "side": "YRFI",
    "price": -111,
    "book": "FanDuel",
    "edge": 0.1492,
    "kelly_pct": 0.0787,
    "stake": 78.71,
    "result": null,
    "runs_in_first": null,
    "pnl": null
  },
  {
    "date": "2026-07-11",
    "game_pk": 823603,
    "away_team": "Boston Red Sox",
    "home_team": "New York Mets",
    "venue": "Citi Field",
    "park_factor": 0.96,
    "temp_f": 72.0,
    "wind_mph": 5.0,
    "dome": false,
    "away_pitcher": "TBD",
    "away_pitcher_1st_era": 4.3,
    "away_pitcher_season_era": 4.3,
    "away_pitcher_k_pct": 22.0,
    "home_pitcher": "Freddy Peralta",
    "home_pitcher_1st_era": 4.3,
    "home_pitcher_season_era": 4.3,
    "home_pitcher_k_pct": 22.0,
    "p_nrfi": 0.0,
    "p_yrfi": 0.0,
    "fair_nrfi": 0,
    "fair_yrfi": 0,
    "verdict": "PITCHER TBD",
    "side": "",
    "price": null,
    "book": "",
    "edge": 0,
    "kelly_pct": 0.0,
    "stake": 0.0,
    "result": null,
    "runs_in_first": null,
    "pnl": null
  },
  {
    "date": "2026-07-11",
    "game_pk": 822953,
    "away_team": "Seattle Mariners",
    "home_team": "Tampa Bay Rays",
    "venue": "Tropicana Field",
    "park_factor": 1.0,
    "temp_f": 72.0,
    "wind_mph": 5.0,
    "dome": false,
    "away_pitcher": "Logan Gilbert",
    "away_pitcher_1st_era": 5.0,
    "away_pitcher_season_era": 3.19,
    "away_pitcher_k_pct": 27.2,
    "home_pitcher": "Griffin Jax",
    "home_pitcher_1st_era": 2.77,
    "home_pitcher_season_era": 3.6,
    "home_pitcher_k_pct": 25.6,
    "p_nrfi": 0.3406,
    "p_yrfi": 0.6594,
    "fair_nrfi": 194,
    "fair_yrfi": -194,
    "verdict": "BET YRFI",
    "side": "YRFI",
    "price": 110,
    "book": "BetMGM",
    "edge": 0.1832,
    "kelly_pct": 0.0874,
    "stake": 87.42,
    "result": null,
    "runs_in_first": null,
    "pnl": null
  },
  {
    "date": "2026-07-11",
    "game_pk": 823844,
    "away_team": "Cleveland Guardians",
    "home_team": "Miami Marlins",
    "venue": "loanDepot park",
    "park_factor": 0.95,
    "temp_f": 72.0,
    "wind_mph": 5.0,
    "dome": true,
    "away_pitcher": "Tanner Bibee",
    "away_pitcher_1st_era": 4.74,
    "away_pitcher_season_era": 4.06,
    "away_pitcher_k_pct": 19.5,
    "home_pitcher": "Eury P\u00e9rez",
    "home_pitcher_1st_era": 4.8,
    "home_pitcher_season_era": 3.84,
    "home_pitcher_k_pct": 27.6,
    "p_nrfi": 0.2815,
    "p_yrfi": 0.7185,
    "fair_nrfi": 255,
    "fair_yrfi": -255,
    "verdict": "BET YRFI",
    "side": "YRFI",
    "price": 112,
    "book": "FanDuel",
    "edge": 0.2468,
    "kelly_pct": 0.1168,
    "stake": 116.78,
    "result": null,
    "runs_in_first": null,
    "pnl": null
  },
  {
    "date": "2026-07-11",
    "game_pk": 824249,
    "away_team": "Philadelphia Phillies",
    "home_team": "Detroit Tigers",
    "venue": "Comerica Park",
    "park_factor": 0.97,
    "temp_f": 84.7,
    "wind_mph": 9.4,
    "dome": false,
    "away_pitcher": "Cristopher S\u00e1nchez",
    "away_pitcher_1st_era": 6.63,
    "away_pitcher_season_era": 2.62,
    "away_pitcher_k_pct": 27.6,
    "home_pitcher": "Casey Mize",
    "home_pitcher_1st_era": 0.0,
    "home_pitcher_season_era": 2.64,
    "home_pitcher_k_pct": 25.7,
    "p_nrfi": 0.3291,
    "p_yrfi": 0.6709,
    "fair_nrfi": 204,
    "fair_yrfi": -204,
    "verdict": "BET YRFI",
    "side": "YRFI",
    "price": 120,
    "book": "BetMGM",
    "edge": 0.2164,
    "kelly_pct": 0.0992,
    "stake": 99.17,
    "result": null,
    "runs_in_first": null,
    "pnl": null
  },
  {
    "date": "2026-07-11",
    "game_pk": 824813,
    "away_team": "Kansas City Royals",
    "home_team": "Baltimore Orioles",
    "venue": "Oriole Park at Camden Yards",
    "park_factor": 1.0,
    "temp_f": 79.8,
    "wind_mph": 5.4,
    "dome": false,
    "away_pitcher": "Noah Cameron",
    "away_pitcher_1st_era": 2.12,
    "away_pitcher_season_era": 4.77,
    "away_pitcher_k_pct": 20.7,
    "home_pitcher": "Kyle Bradish",
    "home_pitcher_1st_era": 1.0,
    "home_pitcher_season_era": 3.75,
    "home_pitcher_k_pct": 23.5,
    "p_nrfi": 0.5747,
    "p_yrfi": 0.4253,
    "fair_nrfi": -135,
    "fair_yrfi": 135,
    "verdict": "BET NRFI",
    "side": "NRFI",
    "price": -110,
    "book": "BetMGM",
    "edge": 0.0509,
    "kelly_pct": 0.0267,
    "stake": 26.72,
    "result": null,
    "runs_in_first": null,
    "pnl": null
  },
  {
    "date": "2026-07-11",
    "game_pk": 822875,
    "away_team": "Houston Astros",
    "home_team": "Texas Rangers",
    "venue": "Globe Life Field",
    "park_factor": 1.01,
    "temp_f": 72.0,
    "wind_mph": 5.0,
    "dome": true,
    "away_pitcher": "Peter Lambert",
    "away_pitcher_1st_era": 1.93,
    "away_pitcher_season_era": 3.26,
    "away_pitcher_k_pct": 22.4,
    "home_pitcher": "Kumar Rocker",
    "home_pitcher_1st_era": 8.4,
    "home_pitcher_season_era": 3.95,
    "home_pitcher_k_pct": 20.4,
    "p_nrfi": 0.2227,
    "p_yrfi": 0.7773,
    "fair_nrfi": 349,
    "fair_yrfi": -349,
    "verdict": "BET YRFI",
    "side": "YRFI",
    "price": 100,
    "book": "FanDuel",
    "edge": 0.2773,
    "kelly_pct": 0.1387,
    "stake": 138.66,
    "result": null,
    "runs_in_first": null,
    "pnl": null
  },
  {
    "date": "2026-07-11",
    "game_pk": 824492,
    "away_team": "Chicago Cubs",
    "home_team": "Cincinnati Reds",
    "venue": "Great American Ball Park",
    "park_factor": 1.08,
    "temp_f": 75.4,
    "wind_mph": 1.1,
    "dome": false,
    "away_pitcher": "Javier Assad",
    "away_pitcher_1st_era": 1.29,
    "away_pitcher_season_era": 4.15,
    "away_pitcher_k_pct": 14.7,
    "home_pitcher": "Nick Lodolo",
    "home_pitcher_1st_era": 2.45,
    "home_pitcher_season_era": 4.68,
    "home_pitcher_k_pct": 17.9,
    "p_nrfi": 0.5115,
    "p_yrfi": 0.4885,
    "fair_nrfi": -105,
    "fair_yrfi": 105,
    "verdict": "BET NRFI",
    "side": "NRFI",
    "price": 116,
    "book": "FanDuel",
    "edge": 0.0485,
    "kelly_pct": 0.0226,
    "stake": 22.59,
    "result": null,
    "runs_in_first": null,
    "pnl": null
  },
  {
    "date": "2026-07-11",
    "game_pk": 823030,
    "away_team": "Atlanta Braves",
    "home_team": "St. Louis Cardinals",
    "venue": "Busch Stadium",
    "park_factor": 0.98,
    "temp_f": 78.9,
    "wind_mph": 6.6,
    "dome": false,
    "away_pitcher": "Reynaldo L\u00f3pez",
    "away_pitcher_1st_era": 5.63,
    "away_pitcher_season_era": 3.18,
    "away_pitcher_k_pct": 21.3,
    "home_pitcher": "Matthew Liberatore",
    "home_pitcher_1st_era": 5.5,
    "home_pitcher_season_era": 5.34,
    "home_pitcher_k_pct": 21.0,
    "p_nrfi": 0.2045,
    "p_yrfi": 0.7955,
    "fair_nrfi": 389,
    "fair_yrfi": -389,
    "verdict": "BET YRFI",
    "side": "YRFI",
    "price": -102,
    "book": "FanDuel",
    "edge": 0.2906,
    "kelly_pct": 0.1467,
    "stake": 146.75,
    "result": null,
    "runs_in_first": null,
    "pnl": null
  },
  {
    "date": "2026-07-11",
    "game_pk": 823276,
    "away_team": "Toronto Blue Jays",
    "home_team": "San Diego Padres",
    "venue": "Petco Park",
    "park_factor": 0.94,
    "temp_f": 72.3,
    "wind_mph": 6.2,
    "dome": false,
    "away_pitcher": "Trey Yesavage",
    "away_pitcher_1st_era": 2.77,
    "away_pitcher_season_era": 3.31,
    "away_pitcher_k_pct": 22.8,
    "home_pitcher": "Walker Buehler",
    "home_pitcher_1st_era": 4.5,
    "home_pitcher_season_era": 5.07,
    "home_pitcher_k_pct": 21.3,
    "p_nrfi": 0.3931,
    "p_yrfi": 0.6069,
    "fair_nrfi": 154,
    "fair_yrfi": -154,
    "verdict": "BET YRFI",
    "side": "YRFI",
    "price": 108,
    "book": "FanDuel",
    "edge": 0.1261,
    "kelly_pct": 0.0607,
    "stake": 60.73,
    "result": null,
    "runs_in_first": null,
    "pnl": null
  },
  {
    "date": "2026-07-11",
    "game_pk": 823926,
    "away_team": "Arizona Diamondbacks",
    "home_team": "Los Angeles Dodgers",
    "venue": "UNIQLO Field at Dodger Stadium",
    "park_factor": 1.0,
    "temp_f": 72.0,
    "wind_mph": 5.0,
    "dome": false,
    "away_pitcher": "Brandon Pfaadt",
    "away_pitcher_1st_era": 1.8,
    "away_pitcher_season_era": 4.84,
    "away_pitcher_k_pct": 18.7,
    "home_pitcher": "Yoshinobu Yamamoto",
    "home_pitcher_1st_era": 4.5,
    "home_pitcher_season_era": 2.49,
    "home_pitcher_k_pct": 25.1,
    "p_nrfi": 0.4118,
    "p_yrfi": 0.5882,
    "fair_nrfi": 143,
    "fair_yrfi": -143,
    "verdict": "BET YRFI",
    "side": "YRFI",
    "price": -115,
    "book": "Caesars",
    "edge": 0.0533,
    "kelly_pct": 0.0286,
    "stake": 28.65,
    "result": null,
    "runs_in_first": null,
    "pnl": null
  }
]