[
  {
    "date": "2026-06-23",
    "game_pk": 822799,
    "away_team": "Houston Astros",
    "home_team": "Toronto Blue Jays",
    "venue": "Rogers Centre",
    "park_factor": 1.03,
    "temp_f": 72.0,
    "wind_mph": 5.0,
    "dome": true,
    "away_pitcher": "Peter Lambert",
    "away_pitcher_1st_era": 2.45,
    "away_pitcher_season_era": 3.23,
    "away_pitcher_k_pct": 22.1,
    "home_pitcher": "Shane Bieber",
    "home_pitcher_1st_era": 4.3,
    "home_pitcher_season_era": 4.3,
    "home_pitcher_k_pct": 22.0,
    "p_nrfi": 0.3716,
    "p_yrfi": 0.6284,
    "fair_nrfi": 169,
    "fair_yrfi": -169,
    "verdict": "BET YRFI",
    "side": "YRFI",
    "price": -110,
    "book": "Caesars",
    "edge": 0.1046,
    "kelly_pct": 0.0549,
    "stake": 54.92,
    "result": null,
    "runs_in_first": null,
    "pnl": null
  },
  {
    "date": "2026-06-23",
    "game_pk": 823365,
    "away_team": "Seattle Mariners",
    "home_team": "Pittsburgh Pirates",
    "venue": "PNC Park",
    "park_factor": 0.97,
    "temp_f": 72.0,
    "wind_mph": 5.0,
    "dome": false,
    "away_pitcher": "George Kirby",
    "away_pitcher_1st_era": 2.4,
    "away_pitcher_season_era": 4.1,
    "away_pitcher_k_pct": 21.1,
    "home_pitcher": "Mitch Keller",
    "home_pitcher_1st_era": 2.4,
    "home_pitcher_season_era": 4.92,
    "home_pitcher_k_pct": 18.4,
    "p_nrfi": 0.5127,
    "p_yrfi": 0.4873,
    "fair_nrfi": -105,
    "fair_yrfi": 105,
    "verdict": "NO BET",
    "side": "NRFI",
    "price": -110,
    "book": "BetOnline.ag",
    "edge": -0.0111,
    "kelly_pct": 0.0,
    "stake": 0.0,
    "result": null,
    "runs_in_first": null,
    "pnl": null
  },
  {
    "date": "2026-06-23",
    "game_pk": 822963,
    "away_team": "Kansas City Royals",
    "home_team": "Tampa Bay Rays",
    "venue": "Tropicana Field",
    "park_factor": 1.0,
    "temp_f": 72.0,
    "wind_mph": 5.0,
    "dome": false,
    "away_pitcher": "Luinder Avila",
    "away_pitcher_1st_era": 19.8,
    "away_pitcher_season_era": 5.5,
    "away_pitcher_k_pct": 20.0,
    "home_pitcher": "Shane McClanahan",
    "home_pitcher_1st_era": 1.93,
    "home_pitcher_season_era": 3.33,
    "home_pitcher_k_pct": 24.0,
    "p_nrfi": 0.2108,
    "p_yrfi": 0.7892,
    "fair_nrfi": 374,
    "fair_yrfi": -374,
    "verdict": "BET YRFI",
    "side": "YRFI",
    "price": -102,
    "book": "FanDuel",
    "edge": 0.2843,
    "kelly_pct": 0.1436,
    "stake": 143.56,
    "result": null,
    "runs_in_first": null,
    "pnl": null
  },
  {
    "date": "2026-06-23",
    "game_pk": 823849,
    "away_team": "Texas Rangers",
    "home_team": "Miami Marlins",
    "venue": "loanDepot park",
    "park_factor": 0.95,
    "temp_f": 72.0,
    "wind_mph": 5.0,
    "dome": true,
    "away_pitcher": "Cal Quantrill",
    "away_pitcher_1st_era": 3.68,
    "away_pitcher_season_era": 3.68,
    "away_pitcher_k_pct": 15.2,
    "home_pitcher": "Sandy Alcantara",
    "home_pitcher_1st_era": 5.63,
    "home_pitcher_season_era": 4.18,
    "home_pitcher_k_pct": 17.8,
    "p_nrfi": 0.2807,
    "p_yrfi": 0.7193,
    "fair_nrfi": 256,
    "fair_yrfi": -256,
    "verdict": "BET YRFI",
    "side": "YRFI",
    "price": 100,
    "book": "FanDuel",
    "edge": 0.2193,
    "kelly_pct": 0.1096,
    "stake": 109.63,
    "result": null,
    "runs_in_first": null,
    "pnl": null
  },
  {
    "date": "2026-06-23",
    "game_pk": 824262,
    "away_team": "New York Yankees",
    "home_team": "Detroit Tigers",
    "venue": "Comerica Park",
    "park_factor": 0.97,
    "temp_f": 72.0,
    "wind_mph": 5.0,
    "dome": false,
    "away_pitcher": "Carlos Rod\u00f3n",
    "away_pitcher_1st_era": 3.86,
    "away_pitcher_season_era": 3.5,
    "away_pitcher_k_pct": 27.2,
    "home_pitcher": "Casey Mize",
    "home_pitcher_1st_era": 0.0,
    "home_pitcher_season_era": 2.58,
    "home_pitcher_k_pct": 25.2,
    "p_nrfi": 0.4674,
    "p_yrfi": 0.5326,
    "fair_nrfi": 114,
    "fair_yrfi": -114,
    "verdict": "BET YRFI",
    "side": "YRFI",
    "price": 116,
    "book": "FanDuel",
    "edge": 0.0696,
    "kelly_pct": 0.0324,
    "stake": 32.42,
    "result": null,
    "runs_in_first": null,
    "pnl": null
  },
  {
    "date": "2026-06-23",
    "game_pk": 822718,
    "away_team": "Philadelphia Phillies",
    "home_team": "Washington Nationals",
    "venue": "Nationals Park",
    "park_factor": 0.96,
    "temp_f": 75.6,
    "wind_mph": 4.5,
    "dome": false,
    "away_pitcher": "Jes\u00fas Luzardo",
    "away_pitcher_1st_era": 0.0,
    "away_pitcher_season_era": 4.2,
    "away_pitcher_k_pct": 26.6,
    "home_pitcher": "Zack Littell",
    "home_pitcher_1st_era": 2.45,
    "home_pitcher_season_era": 5.45,
    "home_pitcher_k_pct": 13.1,
    "p_nrfi": 0.5636,
    "p_yrfi": 0.4364,
    "fair_nrfi": -129,
    "fair_yrfi": 129,
    "verdict": "BET NRFI",
    "side": "NRFI",
    "price": -106,
    "book": "BetOnline.ag",
    "edge": 0.049,
    "kelly_pct": 0.0252,
    "stake": 25.24,
    "result": null,
    "runs_in_first": null,
    "pnl": null
  },
  {
    "date": "2026-06-23",
    "game_pk": 823614,
    "away_team": "Chicago Cubs",
    "home_team": "New York Mets",
    "venue": "Citi Field",
    "park_factor": 0.96,
    "temp_f": 70.0,
    "wind_mph": 2.6,
    "dome": false,
    "away_pitcher": "Edward Cabrera",
    "away_pitcher_1st_era": 1.38,
    "away_pitcher_season_era": 5.21,
    "away_pitcher_k_pct": 21.3,
    "home_pitcher": "Kodai Senga",
    "home_pitcher_1st_era": 12.0,
    "home_pitcher_season_era": 9.0,
    "home_pitcher_k_pct": 24.6,
    "p_nrfi": 0.2362,
    "p_yrfi": 0.7638,
    "fair_nrfi": 323,
    "fair_yrfi": -323,
    "verdict": "BET YRFI",
    "side": "YRFI",
    "price": -105,
    "book": "Caesars",
    "edge": 0.2516,
    "kelly_pct": 0.1289,
    "stake": 128.92,
    "result": null,
    "runs_in_first": null,
    "pnl": null
  },
  {
    "date": "2026-06-23",
    "game_pk": 824501,
    "away_team": "Milwaukee Brewers",
    "home_team": "Cincinnati Reds",
    "venue": "Great American Ball Park",
    "park_factor": 1.08,
    "temp_f": 77.2,
    "wind_mph": 7.8,
    "dome": false,
    "away_pitcher": "Brandon Sproat",
    "away_pitcher_1st_era": 5.25,
    "away_pitcher_season_era": 5.94,
    "away_pitcher_k_pct": 22.8,
    "home_pitcher": "Nick Lodolo",
    "home_pitcher_1st_era": 3.38,
    "home_pitcher_season_era": 6.12,
    "home_pitcher_k_pct": 16.3,
    "p_nrfi": 0.2602,
    "p_yrfi": 0.7398,
    "fair_nrfi": 284,
    "fair_yrfi": -284,
    "verdict": "BET YRFI",
    "side": "YRFI",
    "price": -120,
    "book": "BetMGM",
    "edge": 0.1944,
    "kelly_pct": 0.1069,
    "stake": 106.92,
    "result": null,
    "runs_in_first": null,
    "pnl": null
  },
  {
    "date": "2026-06-23",
    "game_pk": 823690,
    "away_team": "Los Angeles Dodgers",
    "home_team": "Minnesota Twins",
    "venue": "Target Field",
    "park_factor": 0.97,
    "temp_f": 65.1,
    "wind_mph": 3.4,
    "dome": false,
    "away_pitcher": "Justin Wrobleski",
    "away_pitcher_1st_era": 4.5,
    "away_pitcher_season_era": 2.72,
    "away_pitcher_k_pct": 15.8,
    "home_pitcher": "Kendry Rojas",
    "home_pitcher_1st_era": 0.0,
    "home_pitcher_season_era": 1.26,
    "home_pitcher_k_pct": 23.0,
    "p_nrfi": 0.4088,
    "p_yrfi": 0.5912,
    "fair_nrfi": 145,
    "fair_yrfi": -145,
    "verdict": "BET YRFI",
    "side": "YRFI",
    "price": -113,
    "book": "FanDuel",
    "edge": 0.0607,
    "kelly_pct": 0.0323,
    "stake": 32.32,
    "result": null,
    "runs_in_first": null,
    "pnl": null
  },
  {
    "date": "2026-06-23",
    "game_pk": 824584,
    "away_team": "Cleveland Guardians",
    "home_team": "Chicago White Sox",
    "venue": "Rate Field",
    "park_factor": 0.92,
    "temp_f": 72.0,
    "wind_mph": 5.0,
    "dome": false,
    "away_pitcher": "Parker Messick",
    "away_pitcher_1st_era": 0.0,
    "away_pitcher_season_era": 2.7,
    "away_pitcher_k_pct": 26.4,
    "home_pitcher": "Sean Burke",
    "home_pitcher_1st_era": 6.55,
    "home_pitcher_season_era": 3.89,
    "home_pitcher_k_pct": 24.0,
    "p_nrfi": 0.356,
    "p_yrfi": 0.644,
    "fair_nrfi": 181,
    "fair_yrfi": -181,
    "verdict": "BET YRFI",
    "side": "YRFI",
    "price": 123,
    "book": "BetOnline.ag",
    "edge": 0.1956,
    "kelly_pct": 0.0887,
    "stake": 88.66,
    "result": null,
    "runs_in_first": null,
    "pnl": null
  },
  {
    "date": "2026-06-23",
    "game_pk": 823043,
    "away_team": "Arizona Diamondbacks",
    "home_team": "St. Louis Cardinals",
    "venue": "Busch Stadium",
    "park_factor": 0.98,
    "temp_f": 72.0,
    "wind_mph": 5.0,
    "dome": false,
    "away_pitcher": "Eduardo Rodriguez",
    "away_pitcher_1st_era": 6.0,
    "away_pitcher_season_era": 2.45,
    "away_pitcher_k_pct": 17.9,
    "home_pitcher": "Kyle Leahy",
    "home_pitcher_1st_era": 3.86,
    "home_pitcher_season_era": 4.63,
    "home_pitcher_k_pct": 18.7,
    "p_nrfi": 0.2428,
    "p_yrfi": 0.7572,
    "fair_nrfi": 312,
    "fair_yrfi": -312,
    "verdict": "BET YRFI",
    "side": "YRFI",
    "price": -110,
    "book": "BetMGM",
    "edge": 0.2334,
    "kelly_pct": 0.1225,
    "stake": 122.54,
    "result": null,
    "runs_in_first": null,
    "pnl": null
  },
  {
    "date": "2026-06-23",
    "game_pk": 824340,
    "away_team": "Boston Red Sox",
    "home_team": "Colorado Rockies",
    "venue": "Coors Field",
    "park_factor": 1.15,
    "temp_f": 72.0,
    "wind_mph": 5.0,
    "dome": false,
    "away_pitcher": "Sonny Gray",
    "away_pitcher_1st_era": 5.54,
    "away_pitcher_season_era": 3.12,
    "away_pitcher_k_pct": 19.4,
    "home_pitcher": "Sean Sullivan",
    "home_pitcher_1st_era": 0.0,
    "home_pitcher_season_era": 10.29,
    "home_pitcher_k_pct": 11.4,
    "p_nrfi": 0.2994,
    "p_yrfi": 0.7006,
    "fair_nrfi": 234,
    "fair_yrfi": -234,
    "verdict": "BET YRFI",
    "side": "YRFI",
    "price": -122,
    "book": "FanDuel",
    "edge": 0.1511,
    "kelly_pct": 0.0838,
    "stake": 83.83,
    "result": null,
    "runs_in_first": null,
    "pnl": null
  },
  {
    "date": "2026-06-23",
    "game_pk": 824017,
    "away_team": "Baltimore Orioles",
    "home_team": "Los Angeles Angels",
    "venue": "Angel Stadium",
    "park_factor": 0.99,
    "temp_f": 72.0,
    "wind_mph": 5.0,
    "dome": false,
    "away_pitcher": "Shane Baz",
    "away_pitcher_1st_era": 6.0,
    "away_pitcher_season_era": 4.04,
    "away_pitcher_k_pct": 19.8,
    "home_pitcher": "Ryan Johnson",
    "home_pitcher_1st_era": 36.0,
    "home_pitcher_season_era": 12.83,
    "home_pitcher_k_pct": 9.7,
    "p_nrfi": 0.1151,
    "p_yrfi": 0.8849,
    "fair_nrfi": 769,
    "fair_yrfi": -769,
    "verdict": "BET YRFI",
    "side": "YRFI",
    "price": -118,
    "book": "BetMGM",
    "edge": 0.3436,
    "kelly_pct": 0.1873,
    "stake": 187.26,
    "result": null,
    "runs_in_first": null,
    "pnl": null
  },
  {
    "date": "2026-06-23",
    "game_pk": 823286,
    "away_team": "Atlanta Braves",
    "home_team": "San Diego Padres",
    "venue": "Petco Park",
    "park_factor": 0.94,
    "temp_f": 72.0,
    "wind_mph": 5.0,
    "dome": false,
    "away_pitcher": "JR Ritchie",
    "away_pitcher_1st_era": 4.3,
    "away_pitcher_season_era": 4.3,
    "away_pitcher_k_pct": 22.0,
    "home_pitcher": "TBD",
    "home_pitcher_1st_era": 4.3,
    "home_pitcher_season_era": 4.3,
    "home_pitcher_k_pct": 22.0,
    "p_nrfi": 0.0,
    "p_yrfi": 0.0,
    "fair_nrfi": 0,
    "fair_yrfi": 0,
    "verdict": "PITCHER TBD",
    "side": "",
    "price": null,
    "book": "",
    "edge": 0,
    "kelly_pct": 0.0,
    "stake": 0.0,
    "result": null,
    "runs_in_first": null,
    "pnl": null
  },
  {
    "date": "2026-06-23",
    "game_pk": 823210,
    "away_team": "Athletics",
    "home_team": "San Francisco Giants",
    "venue": "Oracle Park",
    "park_factor": 0.9,
    "temp_f": 59.3,
    "wind_mph": 13.1,
    "dome": false,
    "away_pitcher": "Aaron Civale",
    "away_pitcher_1st_era": 6.0,
    "away_pitcher_season_era": 4.91,
    "away_pitcher_k_pct": 15.4,
    "home_pitcher": "Robbie Ray",
    "home_pitcher_1st_era": 3.21,
    "home_pitcher_season_era": 4.07,
    "home_pitcher_k_pct": 22.0,
    "p_nrfi": 0.294,
    "p_yrfi": 0.706,
    "fair_nrfi": 240,
    "fair_yrfi": -240,
    "verdict": "BET YRFI",
    "side": "YRFI",
    "price": -115,
    "book": "BetOnline.ag",
    "edge": 0.1711,
    "kelly_pct": 0.092,
    "stake": 91.95,
    "result": null,
    "runs_in_first": null,
    "pnl": null
  }
]